wordle/__init__.py
wordle/game.py
wordle/valid.txt
wordle/words.txt
wordle_cli-0.2.0.dist-info/METADATA
wordle_cli-0.2.0.dist-info/WHEEL
wordle_cli-0.2.0.dist-info/entry_points.txt
wordle_cli-0.2.0.dist-info/top_level.txt
wordle_cli-0.2.0.dist-info/RECORD
