Metadata-Version: 2.4
Name: wordle-cli
Version: 0.2.0
Summary: Wordle game for your terminal
Author: gautam
Requires-Python: >=3.9
Requires-Dist: pyfiglet
